numpy_ringbuffer/__about__.py
numpy_ringbuffer/__init__.py
numpy_ringbuffer-0.2.2.dist-info/LICENSE.txt
numpy_ringbuffer-0.2.2.dist-info/METADATA
numpy_ringbuffer-0.2.2.dist-info/WHEEL
numpy_ringbuffer-0.2.2.dist-info/top_level.txt
numpy_ringbuffer-0.2.2.dist-info/RECORD
