Metadata-Version: 2.1
Name: numpy_ringbuffer
Version: 0.2.2
Summary: Ring buffer implementation for numpy
Home-page: https://github.com/eric-wieser/numpy_ringbuffer
Author: Eric Wieser
Author-email: wieser.eric+numpy@gmail.com
License: MIT
Download-URL: https://github.com/eric-wieser/numpy_ringbuffer/tarball/v0.2.2
Keywords: numpy,buffer,ringbuffer,circular buffer
Platform: UNKNOWN
Classifier: License :: OSI Approved :: MIT License
Classifier: Intended Audience :: Developers
Classifier: Programming Language :: Python
Classifier: Programming Language :: Python :: 2.7
Classifier: Programming Language :: Python :: 3.5
Classifier: Programming Language :: Python :: 3.6
Classifier: Programming Language :: Python :: 3.7
Classifier: Programming Language :: Python :: 3.8
Classifier: Programming Language :: Python :: 3.9
Classifier: Programming Language :: Python :: 3.10
